llama_index/indices/managed/llama_cloud/BUILD
llama_index/indices/managed/llama_cloud/__init__.py
llama_index/indices/managed/llama_cloud/base.py
llama_index/indices/managed/llama_cloud/retriever.py
llama_index_indices_llama_cloud-0.1.0.dist-info/METADATA
llama_index_indices_llama_cloud-0.1.0.dist-info/WHEEL
llama_index_indices_llama_cloud-0.1.0.dist-info/RECORD
