Metadata-Version: 2.1
Name: llama-index-indices-llama-cloud
Version: 0.1.0
Summary: llama-index indices llama-cloud integration
License: MIT
Author: Logan Markewich
Author-email: logan@llamaindex.ai
Requires-Python: >=3.8.1,<3.12
Classifier: License :: OSI Approved :: MIT License
Classifier: Programming Language :: Python :: 3
Classifier: Programming Language :: Python :: 3.9
Classifier: Programming Language :: Python :: 3.10
Classifier: Programming Language :: Python :: 3.11
Requires-Dist: llama-index-core (>=0.10.0,<0.11.0)
Requires-Dist: llamaindex-py-client (>=0.1.9,<0.2.0)
